sdl2/__init__.py
sdl2/_internal.py
sdl2/_sdl_init.py
sdl2/audio.py
sdl2/blendmode.py
sdl2/clipboard.py
sdl2/cpuinfo.py
sdl2/dll.py
sdl2/endian.py
sdl2/error.py
sdl2/events.py
sdl2/filesystem.py
sdl2/gamecontroller.py
sdl2/gesture.py
sdl2/haptic.py
sdl2/hidapi.py
sdl2/hints.py
sdl2/joystick.py
sdl2/keyboard.py
sdl2/keycode.py
sdl2/loadso.py
sdl2/locale.py
sdl2/log.py
sdl2/messagebox.py
sdl2/metal.py
sdl2/misc.py
sdl2/mouse.py
sdl2/pixels.py
sdl2/platform.py
sdl2/power.py
sdl2/rect.py
sdl2/render.py
sdl2/rwops.py
sdl2/scancode.py
sdl2/sdlgfx.py
sdl2/sdlimage.py
sdl2/sdlmixer.py
sdl2/sdlttf.py
sdl2/sensor.py
sdl2/shape.py
sdl2/stdinc.py
sdl2/surface.py
sdl2/syswm.py
sdl2/timer.py
sdl2/touch.py
sdl2/version.py
sdl2/video.py
sdl2/vulkan.py
sdl2/examples/__init__.py
sdl2/examples/colorpalettes.py
sdl2/examples/draw.py
sdl2/examples/gfxdrawing.py
sdl2/examples/gui.py
sdl2/examples/helloworld.py
sdl2/examples/opengl.py
sdl2/examples/particles.py
sdl2/examples/pixelaccess.py
sdl2/examples/pong.py
sdl2/examples/sdl2hello.py
sdl2/examples/transfomations.py
sdl2/examples/ttf.py
sdl2/examples/resources/button.bmp
sdl2/examples/resources/circle.png
sdl2/examples/resources/font.bmp
sdl2/examples/resources/hello.bmp
sdl2/examples/resources/square.png
sdl2/examples/resources/star.png
sdl2/examples/resources/testimage.svg
sdl2/examples/resources/textentry.bmp
sdl2/examples/resources/tuffy.ttf
sdl2/ext/__init__.py
sdl2/ext/algorithms.py
sdl2/ext/array.py
sdl2/ext/bitmapfont.py
sdl2/ext/color.py
sdl2/ext/colorpalettes.py
sdl2/ext/common.py
sdl2/ext/compat.py
sdl2/ext/draw.py
sdl2/ext/ebs.py
sdl2/ext/events.py
sdl2/ext/image.py
sdl2/ext/msgbox.py
sdl2/ext/particles.py
sdl2/ext/pixelaccess.py
sdl2/ext/renderer.py
sdl2/ext/resources.py
sdl2/ext/sprite.py
sdl2/ext/spritesystem.py
sdl2/ext/surface.py
sdl2/ext/ttf.py
sdl2/ext/uisystem.py
sdl2/ext/window.py
sdl2/test/__init__.py
sdl2/test/audio_test.py
sdl2/test/blendmode_test.py
sdl2/test/clipboard_test.py
sdl2/test/conftest.py
PySDL2-0.9.12.dist-info/AUTHORS.txt
PySDL2-0.9.12.dist-info/COPYING.txt
PySDL2-0.9.12.dist-info/METADATA
PySDL2-0.9.12.dist-info/WHEEL
PySDL2-0.9.12.dist-info/top_level.txt
PySDL2-0.9.12.dist-info/RECORD
